konductor/__init__.py
konductor/init.py
konductor/registry.py
konductor/data/__init__.py
konductor/data/dali.py
konductor/data/_pytorch/__init__.py
konductor/data/_pytorch/cityscapes.py
konductor/data/_pytorch/dataloader.py
konductor/data/_pytorch/mnist.py
konductor/data/_tensorflow/__init__.py
konductor/data/_tensorflow/dataloader.py
konductor/losses/__init__.py
konductor/losses/_pytorch/__init__.py
konductor/losses/_pytorch/base.py
konductor/metadata/__init__.py
konductor/metadata/base_statistic.py
konductor/metadata/manager.py
konductor/metadata/perflogger.py
konductor/metadata/checkpointer/__init__.py
konductor/metadata/checkpointer/_pytorch.py
konductor/metadata/checkpointer/_tensorflow.py
konductor/metadata/checkpointer/base.py
konductor/metadata/database/__init__.py
konductor/metadata/database/interface.py
konductor/metadata/database/metadata.py
konductor/metadata/database/sqlite.py
konductor/metadata/database/tools.py
konductor/metadata/loggers/__init__.py
konductor/metadata/loggers/avg_meter.py
konductor/metadata/loggers/base_writer.py
konductor/metadata/loggers/pq_writer.py
konductor/metadata/loggers/tb_writer.py
konductor/metadata/loggers/wb_writer.py
konductor/metadata/remotesync/__init__.py
konductor/metadata/remotesync/_base.py
konductor/metadata/remotesync/minio.py
konductor/metadata/remotesync/ssh.py
konductor/models/__init__.py
konductor/models/_pytorch/__init__.py
konductor/models/_pytorch/encdec.py
konductor/models/_pytorch/torchvision.py
konductor/models/_tensorflow/__init__.py
konductor/optimizers/__init__.py
konductor/optimizers/_pytorch/__init__.py
konductor/optimizers/_pytorch/base.py
konductor/optimizers/_pytorch/common.py
konductor/optimizers/_pytorch/lamb.py
konductor/scheduler/__init__.py
konductor/scheduler/_pytorch.py
konductor/trainer/__init__.py
konductor/trainer/profiler.py
konductor/trainer/pytorch.py
konductor/trainer/trainer.py
konductor/utilities/__init__.py
konductor/utilities/metadata.py
konductor/utilities/pbar.py
konductor-0.0.8.dist-info/LICENSE
konductor-0.0.8.dist-info/METADATA
konductor-0.0.8.dist-info/WHEEL
konductor-0.0.8.dist-info/entry_points.txt
konductor-0.0.8.dist-info/top_level.txt
konductor-0.0.8.dist-info/RECORD
