Metadata-Version: 2.1
Name: konductor
Version: 0.0.8
Summary: Framework for training generic ml models
Author-email: Bryce Ferenczi <frenzi@hotmail.com.au>
License: Apache License
Project-URL: Homepage, https://github.com/5had3z/konductor
Project-URL: Bug Tracker, https://github.com/5had3z/konductor/issues
Classifier: Development Status :: 2 - Pre-Alpha
Classifier: Intended Audience :: Developers
Classifier: Programming Language :: Python :: 3.10
Classifier: Programming Language :: Python :: 3.11
Classifier: License :: OSI Approved :: Apache Software License
Classifier: Operating System :: OS Independent
Classifier: Natural Language :: English
Requires-Python: >=3.10
License-File: LICENSE
Requires-Dist: numpy
Requires-Dist: pyarrow
Requires-Dist: pandas
Requires-Dist: tensorboard >=1.14
Requires-Dist: tqdm
Requires-Dist: colorama
Requires-Dist: pyyaml
Requires-Dist: typer >=0.9.0
Provides-Extra: dev
Requires-Dist: pytest ; extra == 'dev'
Provides-Extra: remote
Requires-Dist: paramiko ; extra == 'remote'
Requires-Dist: minio ; extra == 'remote'
Provides-Extra: webui
Requires-Dist: dash ; extra == 'webui'
Requires-Dist: plotly ; extra == 'webui'
Requires-Dist: dash-bootstrap-components ; extra == 'webui'
